push_all_in_one/__init__.py
push_all_in_one/one.py
push_all_in_one/setup.py
push_all_in_one/interfaces/__init__.py
push_all_in_one/interfaces/response.py
push_all_in_one/interfaces/schema.py
push_all_in_one/interfaces/send.py
push_all_in_one/push/__init__.py
push_all_in_one/push/custom_email.py
push_all_in_one/push/dingtalk.py
push_all_in_one/push/discord.py
push_all_in_one/push/feishu.py
push_all_in_one/push/i_got.py
push_all_in_one/push/ntfy.py
push_all_in_one/push/one_bot.py
push_all_in_one/push/push_deer.py
push_all_in_one/push/push_plus.py
push_all_in_one/push/qmsg.py
push_all_in_one/push/server_chan_turbo.py
push_all_in_one/push/server_chan_v3.py
push_all_in_one/push/telegram.py
push_all_in_one/push/wechat_app.py
push_all_in_one/push/wechat_robot.py
push_all_in_one/push/wx_pusher.py
push_all_in_one/push/xi_zhi.py
push_all_in_one/utils/__init__.py
push_all_in_one/utils/ajax.py
push_all_in_one/utils/crypto.py
push_all_in_one/utils/helper.py
push_all_in_one/utils/validate.py
push_all_in_one-0.1.4.dist-info/licenses/LICENSE
push_all_in_one-0.1.4.dist-info/METADATA
push_all_in_one-0.1.4.dist-info/WHEEL
push_all_in_one-0.1.4.dist-info/top_level.txt
push_all_in_one-0.1.4.dist-info/RECORD
