Metadata-Version: 2.4
Name: push-all-in-one
Version: 0.1.4
Summary: 多合一推送服务，支持钉钉、企业微信、Telegram、邮件等多种推送方式
Home-page: https://github.com/yourusername/push-all-in-one
Author: Your Name
Author-email: Your Name <your.email@example.com>
License: MIT
Project-URL: Homepage, https://github.com/yourusername/push-all-in-one
Project-URL: Issues, https://github.com/yourusername/push-all-in-one/issues
Keywords: push,notification,dingtalk,wechat,telegram,discord
Classifier: Programming Language :: Python :: 3
Classifier: Programming Language :: Python :: 3.8
Classifier: Programming Language :: Python :: 3.9
Classifier: Programming Language :: Python :: 3.10
Classifier: Programming Language :: Python :: 3.11
Classifier: License :: OSI Approved :: MIT License
Classifier: Operating System :: OS Independent
Requires-Python: >=3.8
License-File: LICENSE
Requires-Dist: requests>=2.31.0
Requires-Dist: pydantic>=2.5.0
Requires-Dist: typing-extensions>=4.8.0
Requires-Dist: PyJWT>=2.8.0
Requires-Dist: urllib3>=2.0.7
Requires-Dist: cryptography>=41.0.5
Requires-Dist: python-dotenv>=1.0.0
Requires-Dist: pycryptodome>=3.19.0
Requires-Dist: aiohttp>=3.8.6
Requires-Dist: httpx>=0.25.0
Dynamic: author
Dynamic: home-page
Dynamic: license-file
Dynamic: requires-python
